{
  "classes": {
    "computer_first": {
      "branch": "computer",
      "year": "first",
      "display_name": "Computer Engineering - 1st Year",
      "timetable": "Timetable not set yet. Contact the class representative.",
      "notices": []
    },
    "computer_second": {
      "branch": "computer",
      "year": "second",
      "display_name": "Computer Engineering - Direct 2nd Year",
      "timetable": "Timetable not set yet. Contact the class representative.",
      "notices": []
    },
    "civil_first": {
      "branch": "civil",
      "year": "first",
      "display_name": "Civil Engineering - 1st Year",
      "timetable": "Timetable not set yet. Contact the class representative.",
      "notices": []
    },
    "civil_second": {
      "branch": "civil",
      "year": "second",
      "display_name": "Civil Engineering - Direct 2nd Year",
      "timetable": "Timetable not set yet. Contact the class representative.",
      "notices": []
    },
    "mechanical_first": {
      "branch": "mechanical",
      "year": "first",
      "display_name": "Mechanical Engineering - 1st Year",
      "timetable": "Timetable not set yet. Contact the class representative.",
      "notices": []
    },
    "mechanical_second": {
      "branch": "mechanical",
      "year": "second",
      "display_name": "Mechanical Engineering - Direct 2nd Year",
      "timetable": "Timetable not set yet. Contact the class representative.",
      "notices": []
    },
    "electrical_first": {
      "branch": "electrical",
      "year": "first",
      "display_name": "Electrical Engineering - 1st Year",
      "timetable": "Timetable not set yet. Contact the class representative.",
      "notices": []
    },
    "electrical_second": {
      "branch": "electrical",
      "year": "second",
      "display_name": "Electrical Engineering - Direct 2nd Year",
      "timetable": "Timetable not set yet. Contact the class representative.",
      "notices": []
    },
    "computer_third": {
      "branch": "computer",
      "year": "third",
      "display_name": "Computer Engineering - 3rd Year",
      "timetable": "Timetable not set yet. Contact the class representative.",
      "notices": []
    },
    "civil_third": {
      "branch": "civil",
      "year": "third",
      "display_name": "Civil Engineering - 3rd Year",
      "timetable": "Timetable not set yet. Contact the class representative.",
      "notices": []
    },
    "mechanical_third": {
      "branch": "mechanical",
      "year": "third",
      "display_name": "Mechanical Engineering - 3rd Year",
      "timetable": "Timetable not set yet. Contact the class representative.",
      "notices": []
    },
    "electrical_third": {
      "branch": "electrical",
      "year": "third",
      "display_name": "Electrical Engineering - 3rd Year",
      "timetable": "Timetable not set yet. Contact the class representative.",
      "notices": []
    }
  }
}